{
	"configurations" : 
	[
		{
			"directories" : 
			[
				{
					"build" : ".",
					"childIndexes" : 
					[
						1
					],
					"hasInstallRule" : true,
					"jsonFile" : "directory-.-Release-ade9140fd065b483201b.json",
					"minimumCMakeVersion" : 
					{
						"string" : "3.12"
					},
					"projectIndex" : 0,
					"source" : ".",
					"targetIndexes" : 
					[
						2,
						3,
						4,
						5
					]
				},
				{
					"build" : "gtest",
					"jsonFile" : "directory-gtest-Release-a2408fe1a73b92c5e636.json",
					"minimumCMakeVersion" : 
					{
						"string" : "3.8"
					},
					"parentIndex" : 0,
					"projectIndex" : 1,
					"source" : "/opt/ros/humble/src/gtest_vendor",
					"targetIndexes" : 
					[
						0,
						1
					]
				}
			],
			"name" : "Release",
			"projects" : 
			[
				{
					"childIndexes" : 
					[
						1
					],
					"directoryIndexes" : 
					[
						0
					],
					"name" : "lbr_fri_ros2",
					"targetIndexes" : 
					[
						2,
						3,
						4,
						5
					]
				},
				{
					"directoryIndexes" : 
					[
						1
					],
					"name" : "gtest",
					"parentIndex" : 0,
					"targetIndexes" : 
					[
						0,
						1
					]
				}
			],
			"targets" : 
			[
				{
					"directoryIndex" : 1,
					"id" : "gtest::@0af4add9fe94340e763e",
					"jsonFile" : "target-gtest-Release-9a36d24a68cb34aaae60.json",
					"name" : "gtest",
					"projectIndex" : 1
				},
				{
					"directoryIndex" : 1,
					"id" : "gtest_main::@0af4add9fe94340e763e",
					"jsonFile" : "target-gtest_main-Release-15b77a77a7d57d6b57c3.json",
					"name" : "gtest_main",
					"projectIndex" : 1
				},
				{
					"directoryIndex" : 0,
					"id" : "lbr_fri_ros2::@6890427a1f51a3e7e1df",
					"jsonFile" : "target-lbr_fri_ros2-Release-b3be1d231ee2f4b1a094.json",
					"name" : "lbr_fri_ros2",
					"projectIndex" : 0
				},
				{
					"directoryIndex" : 0,
					"id" : "lbr_fri_ros2_uninstall::@6890427a1f51a3e7e1df",
					"jsonFile" : "target-lbr_fri_ros2_uninstall-Release-6ab7440e5f747fa61aad.json",
					"name" : "lbr_fri_ros2_uninstall",
					"projectIndex" : 0
				},
				{
					"directoryIndex" : 0,
					"id" : "test_command_interfaces::@6890427a1f51a3e7e1df",
					"jsonFile" : "target-test_command_interfaces-Release-d0db25cdc290fc229d80.json",
					"name" : "test_command_interfaces",
					"projectIndex" : 0
				},
				{
					"directoryIndex" : 0,
					"id" : "uninstall::@6890427a1f51a3e7e1df",
					"jsonFile" : "target-uninstall-Release-1cdcbbc85abe3f6b7336.json",
					"name" : "uninstall",
					"projectIndex" : 0
				}
			]
		}
	],
	"kind" : "codemodel",
	"paths" : 
	{
		"build" : "/home/rosuser/ros2_ws/build/lbr_fri_ros2",
		"source" : "/home/rosuser/ros2_ws/src/lbr_fri_ros2_stack/lbr_fri_ros2"
	},
	"version" : 
	{
		"major" : 2,
		"minor" : 3
	}
}
